flakemaker/__init__.py
flakemaker-1.0.0.post1.dist-info/LICENSE
flakemaker-1.0.0.post1.dist-info/METADATA
flakemaker-1.0.0.post1.dist-info/WHEEL
flakemaker-1.0.0.post1.dist-info/top_level.txt
flakemaker-1.0.0.post1.dist-info/RECORD
