Metadata-Version: 2.1
Name: flakemaker
Version: 1.0.0.post1
Summary: Create snowflakes with encoded data in them.
Author-email: infernostars <infernity@infernity.dev>
License: MIT
Keywords: SNOWFLAKE,ID
Classifier: Development Status :: 5 - Production/Stable
Classifier: Intended Audience :: Developers
Classifier: Topic :: Software Development :: Build Tools
Classifier: License :: OSI Approved :: MIT License
Classifier: Programming Language :: Python :: 3
Classifier: Programming Language :: Python :: 3.10
Classifier: Programming Language :: Python :: 3.11
Classifier: Programming Language :: Python :: 3.12
License-File: LICENSE
